gaelina/__init__.py
gaelina/exceptions.py
gaelina/loaders/__init__.py
gaelina/loaders/dir_loader.py
gaelina/loaders/file_loader.py
gaelina/loaders/file_loaders.py
gaelina/loaders/filter_loader.py
gaelina/loaders/utils.py
gaelina/loaders/special_loaders/__init__.py
gaelina/loaders/special_loaders/x_loader.py
Gaelina-0.2.1.dist-info/LICENSE
Gaelina-0.2.1.dist-info/METADATA
Gaelina-0.2.1.dist-info/WHEEL
Gaelina-0.2.1.dist-info/top_level.txt
Gaelina-0.2.1.dist-info/RECORD
