Metadata-Version: 2.1
Name: Gaelina
Version: 0.2.1
Summary: Config as folder
Home-page: UNKNOWN
Author: Emmanuel PLUOT
License: MIT
Platform: any
Classifier: Programming Language :: Python :: 3 :: Only
Classifier: Programming Language :: Python :: 3.11
Classifier: Programming Language :: Python :: 3.10
Classifier: Programming Language :: Python :: 3.9
Classifier: Development Status :: 1 - Planning
Classifier: Intended Audience :: Developers
Requires-Python: >=3.9
License-File: LICENSE
Requires-Dist: jinja2
Requires-Dist: python-hcl2
Requires-Dist: pyyaml
Requires-Dist: requests
Requires-Dist: toml
Provides-Extra: testing
Requires-Dist: bandit (>=1.8) ; extra == 'testing'
Requires-Dist: flake8 (>=7.1) ; extra == 'testing'
Requires-Dist: pylint (>=3.3) ; extra == 'testing'
Requires-Dist: pytest-cov (>=6.0) ; extra == 'testing'
Requires-Dist: pytest (>=8.3) ; extra == 'testing'
